rlmate/__init__.py
rlmate/argument_parser.py
rlmate/core/__init__.py
rlmate/core/bot.py
rlmate/core/execution.py
rlmate/core/execution_directives.py
rlmate/core/execution_file.py
rlmate/core/settings.py
rlmate/core/tmp.png
rlmate/dict_replay_buffer.py
rlmate/hermes.py
rlmate/hermes_io.py
rlmate/networks/__init__.py
rlmate/networks/attention.py
rlmate/networks/fcn.py
rlmate/networks/linear.py
rlmate/networks/residual.py
rlmate/plot.py
rlmate/pseudo_agent.py
rlmate/replay_buffer.py
rlmate/result.py
rlmate/statistics.py
rlmate/storage.py
rlmate/time_analyzer.py
rlmate/util.py
rlmate-0.3.1.dist-info/METADATA
rlmate-0.3.1.dist-info/WHEEL
rlmate-0.3.1.dist-info/entry_points.txt
rlmate-0.3.1.dist-info/RECORD
