Metadata-Version: 2.1
Name: rlmate
Version: 0.3.1
Summary: tbd.
Author: Timo P. Gros
Author-email: timopgros@cs.uni-saarland.de
Requires-Python: >=3.11,<4.0
Classifier: Development Status :: 2 - Pre-Alpha
Classifier: Operating System :: OS Independent
Classifier: Programming Language :: Python :: 3
Classifier: Programming Language :: Python :: 3.11
Requires-Dist: GitPython (>=3.1.24,<4.0.0)
Requires-Dist: leb128 (>=1.0.4,<2.0.0)
Requires-Dist: matplotlib (>=3.4.3,<4.0.0)
Requires-Dist: numpy
Requires-Dist: pandas (>=1.3.4,<2.0.0)
Requires-Dist: python-telegram-bot (>=13.6,<14.0)
Requires-Dist: scipy (>=1.8.0,<2.0.0)
Requires-Dist: torch (>=2.1.2,<3.0.0)
